algomart/__init__.py
algomart/algorithm/__init__.py
algomart/algorithm/sort/__init__.py
algomart/algorithm/sort/bubble_sort.py
algomart-0.0.2.dist-info/LICENSE
algomart-0.0.2.dist-info/METADATA
algomart-0.0.2.dist-info/WHEEL
algomart-0.0.2.dist-info/top_level.txt
algomart-0.0.2.dist-info/RECORD
