Metadata-Version: 2.1
Name: algomart
Version: 0.0.2
Summary: Collections of algorithms in python
Home-page: https://github.com/AlgoMart/python
Author: Yash Jain
Author-email: yash0307jain@gmail.com
License: MIT
Platform: UNKNOWN
License-File: LICENSE
